commands/__init__.py
commands/exporter.py
commands/flusher.py
commands/migrator.py
metabasepy/__init__.py
metabasepy/client.py
metabasepy/table_parser.py
metabasepy-1.12.0.dist-info/LICENSE
metabasepy-1.12.0.dist-info/METADATA
metabasepy-1.12.0.dist-info/WHEEL
metabasepy-1.12.0.dist-info/top_level.txt
metabasepy-1.12.0.dist-info/RECORD
