Metadata-Version: 2.1
Name: metabasepy
Version: 1.12.0
Summary: Python wrapper for Metabase REST API
Home-page: https://github.com/mertsalik/metabasepy
Author: mertsalik
Author-email: salik@itu.edu.tr
License: The MIT License (MIT)
Platform: UNKNOWN
Classifier: Intended Audience :: Developers
Classifier: License :: OSI Approved :: MIT License
Classifier: Operating System :: OS Independent
Classifier: Programming Language :: Python
Classifier: Programming Language :: Python :: Implementation :: PyPy
Classifier: Topic :: Software Development :: Libraries :: Python Modules
License-File: LICENSE
